universal_music_downloader
