Metadata-Version: 2.4
Name: universal-music-downloader
Version: 0.1.0
Summary: A Python library and command-line tool to download songs from various streaming platforms.
Author-email: Daniel Rico <danialess77@gmail.com>
License-Expression: MIT
Project-URL: Homepage, https://https://github.com/darv-15/Universal-Music-Downloader
Requires-Python: <4.0,>=3.8
License-File: LICENSE
Requires-Dist: requests~=2.32.5
Requires-Dist: yt-dlp~=2025.10.22
Requires-Dist: spotdl>=4.4.3
Dynamic: license-file
